linkml/__init__.py
linkml/_version.py
linkml/cli/__init__.py
linkml/cli/__main__.py
linkml/cli/logging.py
linkml/cli/main.py
linkml/generators/PythonGenNotes.md
linkml/generators/README.md
linkml/generators/__init__.py
linkml/generators/csvgen.py
linkml/generators/dbmlgen.py
linkml/generators/docgen.py
linkml/generators/dotgen.py
linkml/generators/erdiagramgen.py
linkml/generators/excelgen.py
linkml/generators/golanggen.py
linkml/generators/golrgen.py
linkml/generators/graphqlgen.py
linkml/generators/javagen.py
linkml/generators/jsonldcontextgen.py
linkml/generators/jsonldgen.py
linkml/generators/jsonschemagen.py
linkml/generators/linkmlgen.py
linkml/generators/markdowngen.py
linkml/generators/mermaidclassdiagramgen.py
linkml/generators/namespacegen.py
linkml/generators/oocodegen.py
linkml/generators/owlgen.py
linkml/generators/plantumlgen.py
linkml/generators/prefixmapgen.py
linkml/generators/projectgen.py
linkml/generators/protogen.py
linkml/generators/pythongen.py
linkml/generators/rdfgen.py
linkml/generators/shaclgen.py
linkml/generators/shexgen.py
linkml/generators/sparqlgen.py
linkml/generators/sqlalchemygen.py
linkml/generators/sqltablegen.py
linkml/generators/sssomgen.py
linkml/generators/string_template.md
linkml/generators/summarygen.py
linkml/generators/terminusdbgen.py
linkml/generators/typescriptgen.py
linkml/generators/yamlgen.py
linkml/generators/yumlgen.py
linkml/generators/common/__init__.py
linkml/generators/common/build.py
linkml/generators/common/ifabsent_processor.py
linkml/generators/common/lifecycle.py
linkml/generators/common/naming.py
linkml/generators/common/template.py
linkml/generators/common/type_designators.py
linkml/generators/docgen/class.md.jinja2
linkml/generators/docgen/class_diagram.md.jinja2
linkml/generators/docgen/common_metadata.md.jinja2
linkml/generators/docgen/enum.md.jinja2
linkml/generators/docgen/index.md.jinja2
linkml/generators/docgen/index.tex.jinja2
linkml/generators/docgen/schema.md.jinja2
linkml-1.9.4.dist-info/METADATA
linkml-1.9.4.dist-info/WHEEL
linkml-1.9.4.dist-info/entry_points.txt
linkml-1.9.4.dist-info/licenses/LICENSE
linkml-1.9.4.dist-info/RECORD
